vlab_bailer/__init__.py
vlab_bailer/main.py
vlab_bailer-0.1.0.dist-info/METADATA
vlab_bailer-0.1.0.dist-info/WHEEL
vlab_bailer-0.1.0.dist-info/entry_points.txt
vlab_bailer-0.1.0.dist-info/RECORD
